LICENSE
README.md
setup.cfg
setup.py
aminoxii/__init__.py
aminoxii/acm.py
aminoxii/client.py
aminoxii/socket.py
aminoxii/sub_client.py
aminoxii.egg-info/PKG-INFO
aminoxii.egg-info/SOURCES.txt
aminoxii.egg-info/dependency_links.txt
aminoxii.egg-info/requires.txt
aminoxii.egg-info/top_level.txt
aminoxii/asyncfix/__init__.py
aminoxii/asyncfix/acm.py
aminoxii/asyncfix/client.py
aminoxii/asyncfix/socket.py
aminoxii/asyncfix/sub_client.py
aminoxii/lib/__init__.py
aminoxii/lib/util/__init__.py
aminoxii/lib/util/exceptions.py
aminoxii/lib/util/headers.py
aminoxii/lib/util/helpers.py
aminoxii/lib/util/objects.py