Metadata-Version: 2.1
Name: aminoxii
Version: 0.1
Summary: Library for Amino. Discord. 
Home-page: https://github.com/Aimou90/aminoxii
Author: Aimou90
Author-email: aimouu26@gmail.com
License: MIT
Keywords: aminoapps,aminoxii,amino,amino-bot,narvii,api,python,python3,python3.x
Requires-Python: >=3.6
License-File: LICENSE
